Documentation.txt
LICENSE
MANIFEST.in
README
setup.py
txtDC.txt
KF.egg-info/PKG-INFO
KF.egg-info/SOURCES.txt
KF.egg-info/dependency_links.txt
KF.egg-info/requires.txt
KF.egg-info/top_level.txt
kalman_filter/__init__.py
kalman_filter/default.csv
kalman_filter/dodge_cox.csv
kalman_filter/dodge_cox2.csv
kalman_filter/ecKalmanFilter.py
kalman_filter/ecRegression.py
kalman_filter/ecRollingRegression.py
kalman_filter/exc.py
kalman_filter/formatConverter.py
kalman_filter/getFile.py
kalman_filter/icFlexibleLeastSquare.py
kalman_filter/icKalmanFilter.py
kalman_filter/icRegression.py
kalman_filter/icRollingRegression.py
kalman_filter/kalmanFilter.py
kalman_filter/libregression.py
kalman_filter/main.py
kalman_filter/output.csv
kalman_filter/output_fls.csv
kalman_filter/parseFramework.py
kalman_filter/print_exc_plus.py
kalman_filter/projected.csv
kalman_filter/regression.py
kalman_filter/rollingRegression.py
kalman_filter/setup.py
kalman_filter/simulated_portfolio.csv
kalman_filter/simulated_weight.csv
kalman_filter/sine_wave.csv
kalman_filter/sine_wave2.csv
kalman_filter/sine_weight.csv
kalman_filter/test_cfls.py
kalman_filter/test_dodge_cox.csv
kalman_filter/test_dodge_cox_weight.csv
kalman_filter/test_kalmanFilter.py
kalman_filter/timeSeriesFrame.py
kalman_filter/underlying_data.csv
kalman_filter/underlying_weight.csv
kalman_filter/windows.py