Metadata-Version: 1.0
Name: KF
Version: 0.1.3
Summary: Fund performance tracker
Home-page: www.github.com/wingsit/KF
Author: Leon Sit
Author-email: wing1127aishi@gmail.com
License: BSD
Keywords: kalman filter regression fund performance replication tracker
Platform: UNKNOWN
